django_ga_intl_app-4.3.1.dist-info/LICENSE.txt
django_ga_intl_app-4.3.1.dist-info/METADATA
django_ga_intl_app-4.3.1.dist-info/RECORD
django_ga_intl_app-4.3.1.dist-info/WHEEL
django_ga_intl_app-4.3.1.dist-info/top_level.txt
google_analytics/__init__.py
google_analytics/middleware.py
google_analytics/models.py
google_analytics/tasks.py
google_analytics/urls.py
google_analytics/utils.py
google_analytics/views.py
google_analytics/templatetags/__init__.py
google_analytics/templatetags/google_analytics_tags.py
google_analytics/tests/__init__.py
google_analytics/tests/test_ga.py
google_analytics/tests/test_templatetags_google_analytics_tags.py
