Metadata-Version: 2.1
Name: django-ga-intl-app
Version: 4.3.1
Summary: Django Google Analytics app allowing for server side/non-js (fork with international url support and User id tracking)tracking.
Home-page: https://github.com/LaurenBenoit/django-google-analytics-international.git
Author: Praekelt.org
Author-email: dev@praekelt.org
License: BSD
Platform: UNKNOWN
Classifier: Development Status :: 4 - Beta
Classifier: Framework :: Django
Classifier: Intended Audience :: Developers
Classifier: License :: OSI Approved :: BSD License
Classifier: Operating System :: OS Independent
Classifier: Programming Language :: Python :: 2
Classifier: Programming Language :: Python :: 2.7
Classifier: Programming Language :: Python :: 3
Classifier: Programming Language :: Python :: 3.4
Classifier: Programming Language :: Python :: 3.5
Classifier: Programming Language :: Python :: 3.6
Classifier: Topic :: Internet :: WWW/HTTP :: Dynamic Content
Requires-Dist: django (<2.0)
Requires-Dist: django-celery
Requires-Dist: celery (<4.0)
Requires-Dist: requests
Requires-Dist: beautifulsoup4
Requires-Dist: six
